{
  "type": "brewinandchewin:fermenting",
  "container": {
    "item": "brewinandchewin:tankard"
  },
  "experience": 0.6,
  "fermentingtime": 1200,
  "fluiditem": {
    "item": "brewinandchewin:mead"
  },
  "ingredients": [
    {
      "item": "minecraft:sweet_berries"
    },
    {
      "item": "minecraft:sugar_cane"
    },
    {
      "item": "minecraft:sugar_cane"
    },
    {
      "item": "minecraft:melon_slice"
    }
  ],
  "recipe_book_tab": "drinks",
  "result": {
    "item": "brewinandchewin:saccharine_rum"
  },
  "temperature": 4
}